alarms/__init__.py
atligator/__init__.py
atligator/acomplex.py
atligator/argument_collection.py
atligator/atlas.py
atligator/base_scorer.py
atligator/chain_processing.py
atligator/construct_selection.py
atligator/deep_atlas.py
atligator/deprecated.py
atligator/genetic_mutator.py
atligator/geometry.py
atligator/grafting.py
atligator/html_util.py
atligator/io_util.py
atligator/mutation.py
atligator/osprey_util.py
atligator/pdb_util.py
atligator/pocket_miner.py
atligator/prediction_matrix.py
atligator/rosetta_util.py
atligator/similarity_scoring.py
atligator/structure.py
atligator/ui_util.py
atligator/visualization.py
atligator-0.0.10.dist-info/LICENSE
atligator-0.0.10.dist-info/METADATA
atligator-0.0.10.dist-info/WHEEL
atligator-0.0.10.dist-info/top_level.txt
atligator-0.0.10.dist-info/RECORD
