Metadata-Version: 2.1
Name: atligator
Version: 0.0.10
Summary: Atlas based editing of protein interactions
Home-page: https://github.com/Hoecker-Lab/atligator
Author: Josef Kynast
Author-email: josef.kynast@uni-bayreuth.de
Project-URL: Bug Tracker, https://github.com/Hoecker-Lab/atligator/issues
Classifier: Programming Language :: Python :: 3
Classifier: License :: OSI Approved :: GNU General Public License v3 (GPLv3)
Classifier: Operating System :: OS Independent
Classifier: Intended Audience :: Science/Research
Classifier: Topic :: Scientific/Engineering :: Bio-Informatics
Requires-Python: >=3.7
License-File: LICENSE
Requires-Dist: biopython
Requires-Dist: numpy (>=1.13)
Requires-Dist: plotly (>=5.1.0)
Requires-Dist: matplotlib
Requires-Dist: scipy
Requires-Dist: pandas
Requires-Dist: tqdm
